rsaitehu/drawing.py
rsaitehu_drawing-0.0.1.dist-info/METADATA
rsaitehu_drawing-0.0.1.dist-info/WHEEL
rsaitehu_drawing-0.0.1.dist-info/top_level.txt
rsaitehu_drawing-0.0.1.dist-info/RECORD
